ninject/__init__.py
ninject/core.py
ninject/py.typed
ninject/types.py
ninject/_private/__init__.py
ninject/_private/inspect.py
ninject/_private/scope.py
ninject/_private/utils.py
ninject/_private/wrapper.py
ninject-0.0.4.dist-info/METADATA
ninject-0.0.4.dist-info/WHEEL
ninject-0.0.4.dist-info/licenses/LICENSE.txt
ninject-0.0.4.dist-info/RECORD
