Metadata-Version: 2.3
Name: ninject
Version: 0.0.4
Project-URL: Documentation, https://github.com/rmorshea/ninject#readme
Project-URL: Issues, https://github.com/rmorshea/ninject/issues
Project-URL: Source, https://github.com/rmorshea/ninject
Author-email: Ryan Morshead <ryan.morshead@gmail.com>
License-Expression: MIT
License-File: LICENSE.txt
Classifier: Development Status :: 4 - Beta
Classifier: Programming Language :: Python
Classifier: Programming Language :: Python :: 3.10
Classifier: Programming Language :: Python :: 3.11
Classifier: Programming Language :: Python :: 3.12
Classifier: Programming Language :: Python :: Implementation :: CPython
Classifier: Programming Language :: Python :: Implementation :: PyPy
Requires-Python: <4,>=3.10
Requires-Dist: typing-extensions
